plone.app.contentlisting-3.0.6-py3.13-nspkg.pth
plone/app/contentlisting/__init__.py
plone/app/contentlisting/browser.py
plone/app/contentlisting/catalog.py
plone/app/contentlisting/configure.zcml
plone/app/contentlisting/contentlisting.py
plone/app/contentlisting/interfaces.py
plone/app/contentlisting/realobject.py
plone/app/contentlisting/tests/__init__.py
plone/app/contentlisting/tests/base.py
plone/app/contentlisting/tests/integration.rst
plone/app/contentlisting/tests/test_integration_doctest.py
plone/app/contentlisting/tests/test_integration_unit.py
plone_app_contentlisting-3.0.6.dist-info/METADATA
plone_app_contentlisting-3.0.6.dist-info/WHEEL
plone_app_contentlisting-3.0.6.dist-info/entry_points.txt
plone_app_contentlisting-3.0.6.dist-info/namespace_packages.txt
plone_app_contentlisting-3.0.6.dist-info/top_level.txt
plone_app_contentlisting-3.0.6.dist-info/RECORD
