Metadata-Version: 2.4
Name: plone.app.contentlisting
Version: 3.0.6
Summary: Listing of content for the Plone CMS
Home-page: https://pypi.org/project/plone.app.contentlisting
Author: Plone Foundation
Author-email: plone-developers@lists.sourceforge.net
License: GPL version 2
Keywords: content list Plone
Classifier: Development Status :: 5 - Production/Stable
Classifier: Framework :: Plone
Classifier: Framework :: Plone :: Core
Classifier: Framework :: Plone :: 6.0
Classifier: License :: OSI Approved :: GNU General Public License v2 (GPLv2)
Classifier: Programming Language :: Python
Classifier: Programming Language :: Python :: 3.8
Classifier: Programming Language :: Python :: 3.9
Classifier: Programming Language :: Python :: 3.10
Classifier: Programming Language :: Python :: 3.11
Requires-Python: >=3.8
Requires-Dist: setuptools
Requires-Dist: plone.base
Requires-Dist: Products.MimetypesRegistry
Requires-Dist: Products.ZCatalog
Requires-Dist: plone.i18n
Requires-Dist: plone.registry
Requires-Dist: plone.rfc822
Requires-Dist: plone.uuid
Requires-Dist: Zope
Provides-Extra: test
Requires-Dist: plone.app.contenttypes[test]; extra == "test"
Requires-Dist: plone.app.testing; extra == "test"
Requires-Dist: plone.batching; extra == "test"
Requires-Dist: plone.namedfile; extra == "test"
Requires-Dist: plone.testing; extra == "test"
Dynamic: author
Dynamic: author-email
Dynamic: classifier
Dynamic: description
Dynamic: description-content-type
Dynamic: home-page
Dynamic: keywords
Dynamic: license
Dynamic: provides-extra
Dynamic: requires-dist
Dynamic: requires-python
Dynamic: summary
